asyncbbb/__init__.py
asyncbbb-0.1.0.dist-info/LICENSE
asyncbbb-0.1.0.dist-info/WHEEL
asyncbbb-0.1.0.dist-info/METADATA
asyncbbb-0.1.0.dist-info/RECORD
