Metadata-Version: 2.1
Name: asyncbbb
Version: 0.1.0
Summary: 
Author: Sebastian Lübke
Author-email: luebke@gonicus.de
Requires-Python: >=3.8,<4.0
Classifier: Programming Language :: Python :: 3
Classifier: Programming Language :: Python :: 3.8
Classifier: Programming Language :: Python :: 3.9
Requires-Dist: httpx (>=0.23.0,<0.24.0)
Requires-Dist: python-xml2dict (>=0.1.1,<0.2.0)
